evmos/__init__.py
evmos/address_converter.py
evmos/constants.py
evmos/provider.py
evmos/wallet.py
evmos/eip712/__init__.py
evmos/eip712/base.py
evmos/eip712/erc20.py
evmos/eip712/revenue.py
evmos/eip712/staking.py
evmos/eip712/validator.py
evmos/eip712/encoding/__init__.py
evmos/eip712/encoding/decode_amino.py
evmos/eip712/encoding/decode_protobuf.py
evmos/eip712/encoding/encoding.py
evmos/eip712/encoding/registry.py
evmos/eip712/encoding/utils.py
evmos/proto/__init__.py
evmos/proto/authz.py
evmos/proto/erc20.py
evmos/proto/revenue.py
evmos/proto/staking.py
evmos/proto/transactions.py
evmos/proto/utils.py
evmos/proto/validator.py
evmos/proto/autogen/__init__.py
evmos/proto/autogen/py/__init__.py
evmos/proto/autogen/py/cosmos/__init__.py
evmos/proto/autogen/py/cosmos/auth/__init__.py
evmos/proto/autogen/py/cosmos/auth/v1beta1/__init__.py
evmos/proto/autogen/py/cosmos/authz/__init__.py
evmos/proto/autogen/py/cosmos/authz/v1beta1/__init__.py
evmos/proto/autogen/py/cosmos/bank/__init__.py
evmos/proto/autogen/py/cosmos/bank/v1beta1/__init__.py
evmos/proto/autogen/py/cosmos/base/__init__.py
evmos/proto/autogen/py/cosmos/base/abci/__init__.py
evmos/proto/autogen/py/cosmos/base/abci/v1beta1/__init__.py
evmos/proto/autogen/py/cosmos/base/kv/__init__.py
evmos/proto/autogen/py/cosmos/base/kv/v1beta1/__init__.py
evmos/proto/autogen/py/cosmos/base/query/__init__.py
evmos/proto/autogen/py/cosmos/base/query/v1beta1/__init__.py
evmos/proto/autogen/py/cosmos/base/reflection/__init__.py
evmos/proto/autogen/py/cosmos/base/reflection/v1beta1/__init__.py
evmos/proto/autogen/py/cosmos/base/reflection/v2alpha1/__init__.py
evmos/proto/autogen/py/cosmos/base/snapshots/__init__.py
evmos/proto/autogen/py/cosmos/base/snapshots/v1beta1/__init__.py
evmos/proto/autogen/py/cosmos/base/store/__init__.py
evmos/proto/autogen/py/cosmos/base/store/v1beta1/__init__.py
evmos/proto/autogen/py/cosmos/base/tendermint/__init__.py
evmos/proto/autogen/py/cosmos/base/tendermint/v1beta1/__init__.py
evmos-0.1.1.dist-info/LICENSE.md
evmos-0.1.1.dist-info/METADATA
evmos-0.1.1.dist-info/WHEEL
evmos-0.1.1.dist-info/top_level.txt
evmos-0.1.1.dist-info/RECORD
