Metadata-Version: 2.1
Name: evmos
Version: 0.1.1
Summary: Python port of evmos.js - library to interact with Evmos blockchain
Author-email: sterliakov <terlya.stas@gmail.com>
License: GNU GENERAL PUBLIC LICENSE
Project-URL: Home, https://github.com/sterliakov/pyevmos
Project-URL: Source, https://github.com/sterliakov/pyevmos
Project-URL: Issues, https://github.com/sterliakov/pyevmos/issues
Project-URL: Documentation, https://readthedocs.org/projects/pyevmos/badge/?version=latest
Keywords: blockchain,sdk,ethereum
Classifier: Programming Language :: Python :: 3.8
Classifier: Programming Language :: Python :: 3.9
Classifier: Programming Language :: Python :: 3.10
Classifier: Intended Audience :: Developers
Classifier: Topic :: Software Development :: Build Tools
Classifier: License :: OSI Approved :: GNU General Public License v3 (GPLv3)
Classifier: Operating System :: OS Independent
Classifier: Development Status :: 4 - Beta
Classifier: Typing :: Typed
Requires-Python: >=3.8
License-File: LICENSE.md
Requires-Dist: eth-abi (~=3.0)
Requires-Dist: eth-account (~=0.7.0)
Requires-Dist: eth-hash (~=0.3)
Requires-Dist: eth-typing (>=3.1)
Requires-Dist: eth-utils (~=2.0)
Requires-Dist: hexbytes (~=0.3.0)
Requires-Dist: bech32 (~=1.2)
Requires-Dist: typing-extensions (~=4.3)
Requires-Dist: requests (~=2.28)
Requires-Dist: alt-betterproto (~=2.0.1)
Provides-Extra: dev
Requires-Dist: alt-betterproto[compiler] (~=2.0.1) ; extra == 'dev'
Requires-Dist: pre-commit ; extra == 'dev'
Provides-Extra: docs
Requires-Dist: docutils (<0.18,>=0.16) ; extra == 'docs'
Requires-Dist: sphinx (<6.0,>=5.1.1) ; extra == 'docs'
Requires-Dist: sphinx-rtd-theme ; extra == 'docs'
Provides-Extra: test
Requires-Dist: pytest (>=6.4.0) ; extra == 'test'
Requires-Dist: pytest-cov ; extra == 'test'
Requires-Dist: python-dotenv ; extra == 'test'
